colorprint/__init__.py
colorprint/core.py
py_colorprint_cg-0.3.3.dist-info/METADATA
py_colorprint_cg-0.3.3.dist-info/WHEEL
py_colorprint_cg-0.3.3.dist-info/top_level.txt
py_colorprint_cg-0.3.3.dist-info/RECORD
