Metadata-Version: 2.4
Name: py-colorprint-cg
Version: 0.3.3
Home-page: https://github.com/CoolGuy158-Git/colorprint
Author: CoolGuy158-Git
License: MIT
Keywords: terminal color print ANSI style
Classifier: Programming Language :: Python :: 3
Classifier: License :: OSI Approved :: MIT License
Classifier: Operating System :: OS Independent
Requires-Python: >=3.7
Dynamic: author
Dynamic: classifier
Dynamic: description
Dynamic: description-content-type
Dynamic: home-page
Dynamic: keywords
Dynamic: license
Dynamic: requires-python
